llama_index/packs/corrective_rag/__init__.py
llama_index/packs/corrective_rag/base.py
llama_index_packs_corrective_rag-0.3.1.dist-info/METADATA
llama_index_packs_corrective_rag-0.3.1.dist-info/WHEEL
llama_index_packs_corrective_rag-0.3.1.dist-info/licenses/LICENSE
llama_index_packs_corrective_rag-0.3.1.dist-info/RECORD
