Metadata-Version: 2.4
Name: llama-index-packs-corrective-rag
Version: 0.3.1
Summary: llama-index packs corrective_rag paper implementation
Author-email: Ravi Theja <ravi03071991@gmail.com>
Maintainer: ravi-theja
License-Expression: MIT
License-File: LICENSE
Keywords: corrective,corrective_rag,crag,rag,retrieve
Requires-Python: <4.0,>=3.9
Requires-Dist: llama-index-core<0.13,>=0.12.0
Requires-Dist: llama-index-llms-openai<0.5,>=0.4.0
Requires-Dist: llama-index-tools-tavily-research<0.4,>=0.3.0
Requires-Dist: tavily-python<0.4,>=0.3.1
